CHANGES.txt
README.txt
bootstrap.py
buildout.cfg
changes.html
readme.html
setup.py
src/__init__.py
src/pb/__init__.py
src/pb.recipes.pydev.egg-info/PKG-INFO
src/pb.recipes.pydev.egg-info/SOURCES.txt
src/pb.recipes.pydev.egg-info/dependency_links.txt
src/pb.recipes.pydev.egg-info/entry_points.txt
src/pb.recipes.pydev.egg-info/namespace_packages.txt
src/pb.recipes.pydev.egg-info/requires.txt
src/pb.recipes.pydev.egg-info/top_level.txt
src/pb.recipes.pydev.egg-info/zip-safe
src/pb/recipes/__init__.py
src/pb/recipes/pydev/License.txt
src/pb/recipes/pydev/README.txt
src/pb/recipes/pydev/TODO.txt
src/pb/recipes/pydev/__init__.py
src/pb/recipes/pydev/integration.txt
src/pb/recipes/pydev/readme.html
src/pb/recipes/pydev/tests.py