Metadata-Version: 1.0
Name: pb.recipes.pydev
Version: 0.4.5
Summary: Generates an Eclipse Pydev configuration file with path dependencies for an egg
Home-page: http://svn.plone.org/svn/collective/pb.recipes.pydev/
Author: Tiberiu Ichim - Pixelblaster SRL
Author-email: tibi@pixelblaster.ro
License: BSD
Keywords: buildout recipe PyDev eclipse
Platform: UNKNOWN
Classifier: Development Status :: 4 - Beta
Classifier: Environment :: Plugins
Classifier: Framework :: Buildout
Classifier: Framework :: Zope3
Classifier: Intended Audience :: Developers
Classifier: License :: OSI Approved :: BSD License
Classifier: Operating System :: OS Independent
Classifier: Programming Language :: Python
Classifier: Topic :: Software Development :: Build Tools
Classifier: Topic :: Text Editors :: Integrated Development Environments (IDE)
